anchors/__init__.py
anchors/score.py
anchors-0.3.1.dist-info/AUTHORS.rst
anchors-0.3.1.dist-info/LICENSE
anchors-0.3.1.dist-info/METADATA
anchors-0.3.1.dist-info/WHEEL
anchors-0.3.1.dist-info/top_level.txt
anchors-0.3.1.dist-info/RECORD
