Metadata-Version: 2.1
Name: anchors
Version: 0.3.1
Summary: Python package for calculating scores from ancnchor or modifier screens
Home-page: https://github.com/gpp-rnd/anchors
Author: Peter Carl DeWeirdt
Author-email: petedeweirdt@gmail.com
License: MIT license
Keywords: anchors
Classifier: Development Status :: 2 - Pre-Alpha
Classifier: Intended Audience :: Developers
Classifier: License :: OSI Approved :: MIT License
Classifier: Natural Language :: English
Classifier: Programming Language :: Python :: 3
Classifier: Programming Language :: Python :: 3.7
Classifier: Programming Language :: Python :: 3.8
Requires-Python: >=3.5
License-File: LICENSE
License-File: AUTHORS.rst
Requires-Dist: pandas (>=1.1.2)
Requires-Dist: statsmodels (>=0.12)
Requires-Dist: patsy (>=0.5.1)
Requires-Dist: scikit-learn (>=0.23.2)
Requires-Dist: numpy (>=1.19.2)
Requires-Dist: gpplot (>=0.5)
